setup.cfg
setup.py
python_tuya.egg-info/PKG-INFO
python_tuya.egg-info/SOURCES.txt
python_tuya.egg-info/dependency_links.txt
python_tuya.egg-info/requires.txt
python_tuya.egg-info/top_level.txt
python_tuya.egg-info/zip-safe
pytuya/__init__.py
pytuya/aes_cipher.py
pytuya/devices/__init__.py
pytuya/devices/base.py
pytuya/devices/heater.py