Metadata-Version: 1.0
Name: python-tuya
Version: 0.0.2
Summary: Control and read Tuya based devices
Home-page: http://github.com/python-tuya/python-tuya
Author: Jesse Hills
Author-email: UNKNOWN
License: MIT
Platform: UNKNOWN
